raspihive/__init__.py
raspihive/__main__.py
raspihive/helpers.py
raspihive/progress_bars.py
raspihive/threads.py
raspihive-2.0.0.dist-info/LICENSE
raspihive-2.0.0.dist-info/METADATA
raspihive-2.0.0.dist-info/WHEEL
raspihive-2.0.0.dist-info/top_level.txt
raspihive-2.0.0.dist-info/RECORD
