Metadata-Version: 2.1
Name: raspihive
Version: 2.0.0
Summary: RaspiHive toolkit for IOTA Network Entry Points
Home-page: https://github.com/raspihive/raspihive
Author: RaspiHive Team
Author-email: contact@raspihive.org
License: MIT
Platform: UNKNOWN
Classifier: Programming Language :: Python :: 3
Classifier: License :: OSI Approved :: MIT License
Classifier: Operating System :: OS Independent
Requires-Python: >=3.6
Requires-Dist: PyQt5
Requires-Dist: distro (==1.5.0)
